pygeodesy/LICENSE
pygeodesy/__init__.py
pygeodesy/__main__.py
pygeodesy/albers.py
pygeodesy/angles.py
pygeodesy/azimuthal.py
pygeodesy/basics.py
pygeodesy/booleans.py
pygeodesy/cartesianBase.py
pygeodesy/clipy.py
pygeodesy/constants.py
pygeodesy/css.py
pygeodesy/datums.py
pygeodesy/dms.py
pygeodesy/ecef.py
pygeodesy/ecefLocals.py
pygeodesy/elevations.py
pygeodesy/ellipsoidalBase.py
pygeodesy/ellipsoidalBaseDI.py
pygeodesy/ellipsoidalExact.py
pygeodesy/ellipsoidalGeodSolve.py
pygeodesy/ellipsoidalKarney.py
pygeodesy/ellipsoidalNvector.py
pygeodesy/ellipsoidalVincenty.py
pygeodesy/ellipsoids.py
pygeodesy/elliptic.py
pygeodesy/epsg.py
pygeodesy/errors.py
pygeodesy/etm.py
pygeodesy/fmath.py
pygeodesy/formy.py
pygeodesy/frechet.py
pygeodesy/fstats.py
pygeodesy/fsums.py
pygeodesy/gars.py
pygeodesy/geod3solve.py
pygeodesy/geodesici.py
pygeodesy/geodesicw.py
pygeodesy/geodsolve.py
pygeodesy/geohash.py
pygeodesy/geoids.py
pygeodesy/hausdorff.py
pygeodesy/heights.py
pygeodesy/internals.py
pygeodesy/interns.py
pygeodesy/iters.py
pygeodesy/karney.py
pygeodesy/ktm.py
pygeodesy/latlonBase.py
pygeodesy/lazily.py
pygeodesy/lcc.py
pygeodesy/ltp.py
pygeodesy/ltpTuples.py
pygeodesy/mgrs.py
pygeodesy/named.py
pygeodesy/namedTuples.py
pygeodesy/nvectorBase.py
pygeodesy/osgr.py
pygeodesy/points.py
pygeodesy/props.py
pygeodesy/resections.py
pygeodesy/simplify.py
pygeodesy/solveBase.py
pygeodesy/sphericalBase.py
pygeodesy/sphericalNvector.py
pygeodesy/sphericalTrigonometry.py
pygeodesy/streprs.py
pygeodesy/trf.py
pygeodesy/units.py
pygeodesy/unitsBase.py
pygeodesy/ups.py
pygeodesy/utily.py
pygeodesy/utm.py
pygeodesy/utmups.py
pygeodesy/utmupsBase.py
pygeodesy/vector2d.py
pygeodesy/vector3d.py
pygeodesy/vector3dBase.py
pygeodesy/webmercator.py
pygeodesy/wgrs.py
pygeodesy/auxilats/_CX_4.py
pygeodesy/auxilats/_CX_6.py
pygeodesy/auxilats/_CX_8.py
pygeodesy/auxilats/_CX_Rs.py
pygeodesy/auxilats/__init__.py
pygeodesy/auxilats/__main__.py
pygeodesy/auxilats/auxAngle.py
pygeodesy-26.1.16.dist-info/METADATA
pygeodesy-26.1.16.dist-info/WHEEL
pygeodesy-26.1.16.dist-info/top_level.txt
pygeodesy-26.1.16.dist-info/RECORD
