Metadata-Version: 2.1
Name: pygeodesy
Version: 26.1.16
Summary: Pure Python geodesy tools
Home-page: https://GitHub.com/mrJean1/PyGeodesy
Author: Jean M. Brouwers
Author-email: mrJean1@Gmail.com
Maintainer: Jean M. Brouwers
Maintainer-email: mrJean1@Gmail.com
License: MIT
Keywords: AER AGM Albers altitude Andoyer annulus antipode area Arithmetic-Geometric-Mean attitude Authalic auxiliary azimuth azimuthal azimuth-elevation-range bearing bank Barsky Barth beta bi-quadratic boolean cached Cagnoli cartesian Cassini Cassini-Soldner chord circle-intersections circumcenter circumcircle circumradius clip Cohen Cohen-Sutherland Collins composite conformal conformal-sphere conic constants contact-triangle Cook Correia cosines-law coverage curvature cylindrical datum depre
Classifier: Development Status :: 5 - Production/Stable
Classifier: Environment :: Console
Classifier: Intended Audience :: Developers
Classifier: License :: OSI Approved :: MIT License
Classifier: Operating System :: OS Independent
Classifier: Programming Language :: Python
Classifier: Programming Language :: Python :: 2.7
Classifier: Programming Language :: Python :: 3.11
Classifier: Programming Language :: Python :: 3.12
Classifier: Programming Language :: Python :: 3.13
Classifier: Programming Language :: Python :: 3.14
Classifier: Programming Language :: Python :: 3.15
Classifier: Topic :: Software Development
Classifier: Topic :: Scientific/Engineering :: GIS
